[{"duration":"1小时47分","id":3049,"name":"奇谋妙计五福星"},{"duration":"1小时34分","id":3046,"name":"侠盗高飞"},{"duration":"1小时43分","id":3044,"name":"双龙会"},{"duration":"1小时34分","id":3037,"name":"雀圣1"},{"duration":"1小时27分","id":3034,"name":"中喃海保镖"},{"duration":"1小时21分","id":3030,"name":"江湖"},{"duration":"1小时29分","id":3027,"name":"妖兽都市"},{"duration":"1小时34分","id":3025,"name":"新人皮灯笼"},{"duration":"1小时28分","id":3019,"name":"黑狱断肠歌2：无期徒刑"},{"duration":"1小时39分","id":3018,"name":"黑狱断肠歌1：砌生猪肉"},{"duration":"1小时20分","id":3014,"name":"警察故事4：之简单任务"},{"duration":"1小时28分","id":3012,"name":"夜店"},{"duration":"1小时30分","id":3011,"name":"老虎出更1"},{"duration":"1小时33分","id":3010,"name":"一个烂赌的传说"},{"duration":"1小时50分","id":3009,"name":"五亿探长雷洛传2：父子情仇"},{"duration":"2小时7分","id":3008,"name":"五亿探长雷洛传1：雷老虎"},{"duration":"1小时32分","id":3006,"name":"大内密探灵灵狗"},{"duration":"1小时47分","id":2986,"name":"龙在边缘"},{"duration":"1小时43分","id":2977,"name":"疯狂的石头"},{"duration":"1小时54分","id":2974,"name":"鬼请你睇戏"},{"duration":"1小时31分","id":2967,"name":"鬼媾人"},{"duration":"1小时28分","id":2966,"name":"鬼赌鬼"},{"duration":"1小时41分","id":2964,"name":"赌神3"},{"duration":"1小时35分","id":2963,"name":"超级无敌追女仔"},{"duration":"1小时59分","id":2957,"name":"黑金"},{"duration":"1小时34分","id":2956,"name":"黑心鬼"},{"duration":"1小时40分","id":2953,"name":"绝世好宾"},{"duration":"1小时26分","id":2952,"name":"老鼠爱上猫"},{"duration":"1小时32分","id":2946,"name":"霹雳大喇叭"},{"duration":"1小时25分","id":2944,"name":"逃学英雄传"},{"duration":"1小时24分","id":2942,"name":"香港第一凶宅"},{"duration":"1小时34分","id":2940,"name":"胭脂扣"},{"duration":"2小时0分","id":2939,"name":"饮食男女"},{"duration":"1小时33分","id":2938,"name":"幽灵情书"},{"duration":"1小时31分","id":2937,"name":"缘份"},{"duration":"1小时26分","id":2935,"name":"追魂伞"},{"duration":"1小时21分","id":2896,"name":"飞龙再生"},{"duration":"1小时34分","id":2895,"name":"霸王花"},{"duration":"1小时37分","id":2874,"name":"小狐仙"},{"duration":"1小时26分","id":2872,"name":"小飞侠"},{"duration":"1小时22分","id":2869,"name":"卫斯理之老猫"},{"duration":"1小时29分","id":2868,"name":"少年赌圣"},{"duration":"奶瓶新视频","id":2858,"name":"开心鬼放暑假"},{"duration":"1小时29分","id":2856,"name":"吉星拱照"},{"duration":"1小时19分","id":2837,"name":"出土奇兵"},{"duration":"1小时25分","id":2825,"name":"炭烧凶咒"},{"duration":"1小时43分","id":2824,"name":"星月童话"},{"duration":"奶瓶新视频","id":2823,"name":"天黑请闭眼"},{"duration":"奶瓶新视频","id":2817,"name":"全城戒备"},{"duration":"奶瓶新视频","id":2815,"name":"猛鬼学堂"},{"duration":"奶瓶新视频","id":2810,"name":"生化寿尸"},{"duration":"1小时31分","id":2796,"name":"第一诫"},{"duration":"1小时29分","id":2795,"name":"双龙出海"},{"duration":"1小时25分","id":2793,"name":"上天救命"},{"duration":"1小时52分","id":2792,"name":"上车走吧"},{"duration":"1小时30分","id":2774,"name":"喜马拉亚星"},{"duration":"1小时34分","id":2767,"name":"夜半无人尸语时"},{"duration":"1小时27分","id":2758,"name":"旋风小子"},{"duration":"奶瓶新视频","id":2755,"name":"最佳拍档4：千里救差婆"},{"duration":"奶瓶新视频","id":2739,"name":"猛鬼食人胎"},{"duration":"1小时28分","id":2738,"name":"生人勿近之问米"},{"duration":"1小时42分","id":2718,"name":"瘦虎肥龙"},{"duration":"奶瓶新视频","id":2683,"name":"未来警察"},{"duration":"奶瓶新视频","id":2666,"name":"天地玄门"},{"duration":"奶瓶新视频","id":2636,"name":"妖魔奇兵"},{"duration":"1小时35分","id":2613,"name":"我老婆唔系人"},{"duration":"奶瓶新视频","id":2594,"name":"回转寿尸"},{"duration":"奶瓶新视频","id":2593,"name":"鬼名模"},{"duration":"奶瓶新视频","id":2585,"name":"东京攻略"},{"duration":"奶瓶新视频","id":2584,"name":"三岔口"},{"duration":"1小时43分","id":2581,"name":"斗牛"},{"duration":"1小时29分","id":2576,"name":"杀手蝴蝶梦"},{"duration":"1小时40分","id":2570,"name":"绝色神偷"},{"duration":"1小时40分","id":2569,"name":"着牛仔裤的钟馗"},{"duration":"1小时40分","id":2565,"name":"特警屠龙"},{"duration":"1小时40分","id":2558,"name":"最佳拍档3：女皇密令"},{"duration":"1小时40分","id":2557,"name":"最佳拍档2：大显神通"},{"duration":"1小时32分","id":2556,"name":"最佳拍档1"},{"duration":"1小时38分","id":2551,"name":"恋爱通告"},{"duration":"1小时54分","id":2543,"name":"画皮"},{"duration":"1小时43分","id":2538,"name":"矮仔多情"},{"duration":"1小时31分","id":2523,"name":"一本漫画闯天涯2"},{"duration":"奶瓶新视频","id":2516,"name":"精武风云：陈真"},{"duration":"1小时29分","id":2513,"name":"至尊无上之永霸天下"},{"duration":"1小时30分","id":2511,"name":"花田喜事2010"},{"duration":"2小时6分","id":2506,"name":"辣手神探"},{"duration":"1小时29分","id":2505,"name":"逃学外传"},{"duration":"1小时35分","id":2503,"name":"阴阳路5：一见发财"},{"duration":"1小时41分","id":2495,"name":"中华赌侠"},{"duration":"1小时23分","id":2492,"name":"僵尸福星仔"},{"duration":"1小时41分","id":2481,"name":"O记三合会档案"},{"duration":"奶瓶新视频","id":2472,"name":"独孤九剑"},{"duration":"1小时20分","id":2456,"name":"孔雀王子"},{"duration":"1小时23分","id":2455,"name":"文雀"},{"duration":"1小时37分","id":2448,"name":"旺角卡门"},{"duration":"1小时38分","id":2433,"name":"僵尸新战士"},{"duration":"1小时34分","id":2432,"name":"僵尸医生"},{"duration":"1小时26分","id":2431,"name":"何必有我"},{"duration":"1小时27分","id":2429,"name":"Office有鬼"},{"duration":"1小时38分","id":2428,"name":"阴阳路之升棺发财"},{"duration":"1小时35分","id":2427,"name":"阴阳路2：我在你左右"},{"duration":"1小时38分","id":2426,"name":"阴阳路"},{"duration":"1小时15分","id":2424,"name":"原振侠与卫斯理"},{"duration":"1小时47分","id":2419,"name":"夕阳天使"},{"duration":"1小时26分","id":2418,"name":"没完没了"},{"duration":"1小时41分","id":2413,"name":"新英雄本色"},{"duration":"1小时35分","id":2407,"name":"我左眼见到鬼"},{"duration":"1小时36分","id":2404,"name":"新天龙八部之天山童姥"},{"duration":"2小时9分","id":2403,"name":"唐山大地震"},{"duration":"1小时34分","id":2401,"name":"天若有情3：烽火佳人"},{"duration":"1小时39分","id":2396,"name":"十兄弟"},{"duration":"1小时37分","id":2394,"name":"水浒传之英雄本色"},{"duration":"1小时36分","id":2392,"name":"情癫大圣"},{"duration":"1小时31分","id":2389,"name":"六指琴魔"},{"duration":"1小时44分","id":2388,"name":"千机变"},{"duration":"1小时37分","id":2382,"name":"买凶拍人"},{"duration":"1小时29分","id":2380,"name":"伦文叙老点柳先开"},{"duration":"1小时47分","id":2376,"name":"烈火战车2：极速传说"},{"duration":"1小时13分","id":2371,"name":"新虎兄豹弟"},{"duration":"1小时51分","id":2370,"name":"龙在江湖"},{"duration":"1小时34分","id":2369,"name":"呖咕呖咕新年财"},{"duration":"1小时31分","id":2362,"name":"僵尸叔叔"},{"duration":"1小时43分","id":2356,"name":"给爸爸的信"},{"duration":"1小时54分","id":2352,"name":"风声"},{"duration":"1小时42分","id":2348,"name":"杜拉拉升职记"},{"duration":"1小时43分","id":2346,"name":"大佬爱美丽"},{"duration":"1小时32分","id":2344,"name":"东方三侠2"},{"duration":"1小时23分","id":2343,"name":"东方三侠1"},{"duration":"1小时28分","id":2341,"name":"大丈夫日记"},{"duration":"1小时29分","id":2340,"name":"大块头有大智慧"},{"duration":"1小时36分","id":2339,"name":"大灌篮"},{"duration":"1小时29分","id":2337,"name":"长短脚之恋"},{"duration":"1小时53分","id":2336,"name":"赤道"},{"duration":"1小时39分","id":2326,"name":"机器侠"},{"duration":"1小时46分","id":2324,"name":"绝代双骄"},{"duration":"1小时45分","id":2318,"name":"江湖告急"},{"duration":"1小时46分","id":2312,"name":"纵横四海"},{"duration":"1小时43分","id":2311,"name":"黑白森林"},{"duration":"1小时42分","id":2310,"name":"决战紫禁之巅"},{"duration":"1小时27分","id":2305,"name":"开心鬼撞鬼"},{"duration":"2小时4分","id":2301,"name":"至尊无上"},{"duration":"1小时31分","id":2300,"name":"画中仙"},{"duration":"1小时29分","id":2296,"name":"天若有情"},{"duration":"1小时37分","id":2289,"name":"黑侠"},{"duration":"1小时32分","id":2277,"name":"阿飞正传"},{"duration":"1小时36分","id":2271,"name":"赌圣3：无名小子"},{"duration":"1小时37分","id":2269,"name":"赌圣2：街头赌圣"},{"duration":"1小时24分","id":2254,"name":"黑涩会2：以和为贵"},{"duration":"1小时35分","id":2253,"name":"黑涩会1：龙城岁月"},{"duration":"1小时42分","id":2247,"name":"中华英雄"},{"duration":"1小时34分","id":2244,"name":"太极张三丰"},{"duration":"1小时48分","id":2243,"name":"烈火战车"},{"duration":"1小时45分","id":2241,"name":"末路狂花"},{"duration":"1小时45分","id":2236,"name":"至尊计状元才"},{"duration":"1小时34分","id":2228,"name":"超级学校霸王"},{"duration":"1小时36分","id":2226,"name":"摩登如来神掌"},{"duration":"1小时41分","id":2223,"name":"金枝玉叶1"},{"duration":"1小时48分","id":2222,"name":"金枝玉叶2"},{"duration":"1小时58分","id":2221,"name":"集结号"},{"duration":"1小时33分","id":1824,"name":"南北少林"},{"duration":"1小时51分","id":1823,"name":"单身男女1"},{"duration":"1小时53分","id":1799,"name":"天下无贼"},{"duration":"2小时12分","id":1791,"name":"宝贝计划"},{"duration":"1小时47分","id":1781,"name":"快餐车"},{"duration":"奶瓶新视频","id":1769,"name":"我的野蛮女友1"},{"duration":"1小时31分","id":1766,"name":"新少林五祖"},{"duration":"1小时34分","id":1752,"name":"杀破狼：贪狼"},{"duration":"奶瓶新视频","id":1751,"name":"枪王"},{"duration":"1小时44分","id":1748,"name":"特务迷城"},{"duration":"1小时58分","id":1743,"name":"玻璃樽"},{"duration":"1小时28分","id":1742,"name":"画皮之阴阳法王"},{"duration":"1小时33分","id":1740,"name":"瘦身男女"},{"duration":"1小时19分","id":1736,"name":"神探"},{"duration":"1小时43分","id":1730,"name":"精武英雄"},{"duration":"1小时48分","id":1723,"name":"线人"},{"duration":"1小时59分","id":1720,"name":"狄仁杰之通天帝国"},{"duration":"1小时26分","id":1714,"name":"茅山斗僵尸"},{"duration":"1小时34分","id":1702,"name":"警察故事3：超级警察"},{"duration":"1小时47分","id":1676,"name":"我是谁"},{"duration":"1小时23分","id":1668,"name":"九星报喜"},{"duration":"1小时31分","id":1647,"name":"一个好人"},{"duration":"1小时40分","id":1535,"name":"倚天屠龙记之魔教教主"},{"duration":"2小时5分","id":1532,"name":"风云1：雄霸天下"},{"duration":"1小时47分","id":1531,"name":"风云2"},{"duration":"1小时42分","id":1529,"name":"新龙门客栈"},{"duration":"1小时40分","id":1517,"name":"蜀山传"},{"duration":"1小时32分","id":1515,"name":"青蛇"},{"duration":"1小时47分","id":1512,"name":"笑傲江湖2：东方不败"},{"duration":"1小时56分","id":1511,"name":"笑傲江湖1"},{"duration":"1小时37分","id":1451,"name":"黄飞鸿5：龙城歼霸"},{"duration":"1小时50分","id":1440,"name":"黄飞鸿之铁鸡斗蜈蚣"},{"duration":"1小时39分","id":1439,"name":"黄飞鸿6：西域雄狮"},{"duration":"1小时51分","id":1438,"name":"黄飞鸿3：狮王争霸"},{"duration":"1小时43分","id":1394,"name":"叶问1"},{"duration":"1小时45分","id":1393,"name":"叶问2"},{"duration":"2小时5分","id":1387,"name":"追龙"},{"duration":"1小时35分","id":1379,"name":"方世玉1"},{"duration":"1小时55分","id":1377,"name":"无间道2"},{"duration":"1小时57分","id":1375,"name":"无极"},{"duration":"1小时38分","id":1372,"name":"无间道1"},{"duration":"1小时35分","id":1362,"name":"新上海滩"},{"duration":"2小时0分","id":1359,"name":"扑克王"},{"duration":"1小时35分","id":1356,"name":"赌侠大战拉斯维加斯"},{"duration":"1小时51分","id":1355,"name":"赌侠1999"},{"duration":"2小时10分","id":1354,"name":"喋血街头"},{"duration":"2小时5分","id":1350,"name":"赌神"},{"duration":"1小时46分","id":1345,"name":"春娇与志明"},{"duration":"1小时23分","id":1344,"name":"神勇双响炮2"},{"duration":"1小时29分","id":1343,"name":"神勇双响炮1"},{"duration":"1小时45分","id":1335,"name":"倩女幽魂3"},{"duration":"1小时39分","id":1334,"name":"倩女幽魂2"},{"duration":"1小时32分","id":1333,"name":"倩女幽魂1"},{"duration":"1小时50分","id":1308,"name":"满城尽带黄金甲"},{"duration":"1小时58分","id":1302,"name":"英雄本色3"},{"duration":"1小时43分","id":1301,"name":"英雄本色2"},{"duration":"1小时54分","id":1298,"name":"卧虎藏龙"},{"duration":"1小时58分","id":1293,"name":"非诚勿扰2"},{"duration":"2小时3分","id":1292,"name":"非诚勿扰1"},{"duration":"1小时41分","id":1280,"name":"疯狂的赛车"},{"duration":"1小时43分","id":1254,"name":"头文字D"},{"duration":"1小时28分","id":1226,"name":"杀破狼"},{"duration":"1小时34分","id":1193,"name":"英雄本色1"},{"duration":"1小时33分","id":1110,"name":"暗战2"},{"duration":"1小时31分","id":1109,"name":"暗战1"},{"duration":"1小时32分","id":1083,"name":"师兄撞鬼"},{"duration":"1小时36分","id":1080,"name":"破坏之王"},{"duration":"1小时27分","id":1078,"name":"喜剧之王"},{"duration":"1小时37分","id":1076,"name":"鹿鼎记2"},{"duration":"1小时28分","id":1073,"name":"济公"},{"duration":"1小时46分","id":1070,"name":"少林足球"},{"duration":"1小时33分","id":1069,"name":"漫画威龙"},{"duration":"1小时39分","id":1064,"name":"审死官"},{"duration":"1小时20分","id":1062,"name":"回魂夜"},{"duration":"1小时31分","id":1054,"name":"千王之王2000"},{"duration":"奶瓶新视频","id":1052,"name":"行运一条龙"},{"duration":"奶瓶新视频","id":1051,"name":"一本漫画闯天涯"},{"duration":"1小时25分","id":1049,"name":"算死草"},{"duration":"1小时31分","id":1048,"name":"食神"},{"duration":"1小时28分","id":1046,"name":"长江7号"}]